zowe/zos_jobs_for_zowe_sdk/__init__.py
zowe/zos_jobs_for_zowe_sdk/jobs.py
zowe_zos_jobs_for_zowe_sdk-0.5.0.dist-info/METADATA
zowe_zos_jobs_for_zowe_sdk-0.5.0.dist-info/WHEEL
zowe_zos_jobs_for_zowe_sdk-0.5.0.dist-info/top_level.txt
zowe_zos_jobs_for_zowe_sdk-0.5.0.dist-info/RECORD
